{"ProjectName":"Double_Test","Details":"","fileName":"Double_Test","fileFolder":"D:\\RichCaptionEditor\\RCE\\Assets\\TestFiles","videoFile":"Double.mp4","videoFolder":"D:\\RichCaptionEditor\\RCE\\Assets\\Video","StyleGroups":[{"Name":"","Styles":[{"Name":"Default","Description":"","element":{"Name":"Default","Value":""},"featureFilter":5},{"Name":"Default Speech","Description":"","element":{"Name":"Default","Value":"Speech"},"featureFilter":7},{"Name":"Default Speech2","Description":"","element":{"Name":"Default","Value":"Speech2"},"featureFilter":7},{"Name":"Default Speech_copy","Description":"","element":{"Name":"Default","Value":"Speech_copy"},"featureFilter":7},{"Name":"Default Speech2","Description":"","element":{"Name":"Default","Value":"Speech2"},"featureFilter":7},{"Name":"Bold","Description":"","element":{"Name":"b","Value":""},"featureFilter":4},{"Name":"Italic","Description":"","element":{"Name":"i","Value":""},"featureFilter":4},{"Name":"Underline","Description":"","element":{"Name":"u","Value":""},"featureFilter":4},{"Name":"Strikethrough","Description":"","element":{"Name":"s","Value":""},"featureFilter":4},{"Name":"","Description":"","element":{"Name":"x","Value":""},"featureFilter":4},{"Name":"","Description":"","element":{"Name":"b","Value":""},"featureFilter":4},{"Name":"","Description":"","element":{"Name":"123","Value":""},"featureFilter":4},{"Name":"","Description":"","element":{"Name":"Word Title","Value":""},"featureFilter":4},{"Name":"","Description":"","element":{"Name":"id_withoutspace","Value":""},"featureFilter":4},{"Name":"","Description":"","element":{"Name":"Caption Box ","Value":""},"featureFilter":2},{"Name":"","Description":"","element":{"Name":"Caption Box  2","Value":""},"featureFilter":2},{"Name":"","Description":"","element":{"Name":"Caption Box  3","Value":""},"featureFilter":2},{"Name":"","Description":"","element":{"Name":"Caption Box  4","Value":""},"featureFilter":2},{"Name":"","Description":"","element":{"Name":"Caption Box  5","Value":""},"featureFilter":2},{"Name":"","Description":"","element":{"Name":"Caption Box  6","Value":""},"featureFilter":2},{"Name":"","Description":"","element":{"Name":"Caption Box  7","Value":""},"featureFilter":2},{"Name":"","Description":"","element":{"Name":"Caption Box  8","Value":""},"featureFilter":2}]}],"CueGroups":[{"Name":"Speech","Cues":[{"Identifier":"1","StartTime":46.941001892089847,"EndTime":49.402000427246097,"RegionFeature":"","CueElement":{"Name":"","Value":""},"TextSegments":[{"Content":[{"c":89,"elements":[]},{"c":111,"elements":[]},{"c":117,"elements":[]},{"c":39,"elements":[]},{"c":114,"elements":[]},{"c":101,"elements":[]},{"c":32,"elements":[]},{"c":97,"elements":[]},{"c":32,"elements":[]},{"c":115,"elements":[]},{"c":109,"elements":[]},{"c":97,"elements":[]},{"c":114,"elements":[]},{"c":116,"elements":[]},{"c":32,"elements":[]},{"c":105,"elements":[]},{"c":110,"elements":[]},{"c":115,"elements":[]},{"c":117,"elements":[]},{"c":114,"elements":[]},{"c":97,"elements":[]},{"c":110,"elements":[]},{"c":99,"elements":[]},{"c":101,"elements":[]},{"c":32,"elements":[]},{"c":109,"elements":[]},{"c":97,"elements":[]},{"c":110,"elements":[]},{"c":44,"elements":[]},{"c":10,"elements":[]},{"c":97,"elements":[]},{"c":114,"elements":[]},{"c":101,"elements":[]},{"c":110,"elements":[]},{"c":39,"elements":[]},{"c":116,"elements":[]},{"c":32,"elements":[]},{"c":121,"elements":[]},{"c":111,"elements":[]},{"c":117,"elements":[]},{"c":44,"elements":[]},{"c":32,"elements":[]},{"c":77,"elements":[]},{"c":114,"elements":[]},{"c":46,"elements":[]},{"c":32,"elements":[]},{"c":78,"elements":[]},{"c":101,"elements":[]},{"c":102,"elements":[]},{"c":102,"elements":[]},{"c":63,"elements":[]},{"c":10,"elements":[]}],"StringContent":[{"s":"You're a smart insurance man,\naren't you, Mr. Neff?\n","elements":[]}]}],"CurrentTextSegment":0},{"Identifier":"2","StartTime":49.44300079345703,"EndTime":52.02899932861328,"RegionFeature":"","CueElement":{"Name":"","Value":""},"TextSegments":[{"Content":[{"c":87,"elements":[]},{"c":101,"elements":[]},{"c":108,"elements":[]},{"c":108,"elements":[]},{"c":44,"elements":[]},{"c":32,"elements":[]},{"c":73,"elements":[{"Name":"i","Value":""}]},{"c":39,"elements":[{"Name":"i","Value":""}]},{"c":118,"elements":[{"Name":"i","Value":""}]},{"c":101,"elements":[{"Name":"i","Value":""}]},{"c":32,"elements":[{"Name":"i","Value":""}]},{"c":98,"elements":[{"Name":"i","Value":""}]},{"c":101,"elements":[{"Name":"i","Value":""}]},{"c":101,"elements":[{"Name":"i","Value":""}]},{"c":110,"elements":[{"Name":"i","Value":""}]},{"c":32,"elements":[{"Name":"b","Value":""}]},{"c":97,"elements":[{"Name":"b","Value":""}]},{"c":116,"elements":[{"Name":"b","Value":""}]},{"c":32,"elements":[{"Name":"b","Value":""}]},{"c":105,"elements":[{"Name":"b","Value":""}]},{"c":116,"elements":[{"Name":"b","Value":""}]},{"c":32,"elements":[{"Name":"b","Value":""}]},{"c":49,"elements":[{"Name":"b","Value":""}]},{"c":49,"elements":[{"Name":"b","Value":""}]},{"c":32,"elements":[{"Name":"b","Value":""}]},{"c":121,"elements":[{"Name":"b","Value":""}]},{"c":101,"elements":[{"Name":"b","Value":""}]},{"c":97,"elements":[{"Name":"b","Value":""}]},{"c":114,"elements":[{"Name":"b","Value":""}]},{"c":115,"elements":[{"Name":"b","Value":""}]},{"c":10,"elements":[]},{"c":68,"elements":[]},{"c":111,"elements":[]},{"c":105,"elements":[]},{"c":110,"elements":[]},{"c":103,"elements":[]},{"c":32,"elements":[]},{"c":112,"elements":[]},{"c":114,"elements":[]},{"c":101,"elements":[]},{"c":116,"elements":[]},{"c":116,"elements":[]},{"c":121,"elements":[]},{"c":32,"elements":[]},{"c":119,"elements":[]},{"c":101,"elements":[]},{"c":108,"elements":[]},{"c":108,"elements":[]},{"c":63,"elements":[]},{"c":10,"elements":[]}],"StringContent":[{"s":"Well, ","elements":[]},{"s":"I've been","elements":[{"Name":"i","Value":""}]},{"s":" at it 11 years","elements":[{"Name":"b","Value":""}]},{"s":"\nDoing pretty well?\n","elements":[]}]}],"CurrentTextSegment":0},{"Identifier":"3","StartTime":52.07099914550781,"EndTime":53.448001861572269,"RegionFeature":"","CueElement":{"Name":"","Value":""},"TextSegments":[{"Content":[{"c":73,"elements":[]},{"c":116,"elements":[]},{"c":39,"elements":[]},{"c":115,"elements":[]},{"c":32,"elements":[]},{"c":97,"elements":[]},{"c":32,"elements":[]},{"c":108,"elements":[]},{"c":105,"elements":[]},{"c":118,"elements":[]},{"c":105,"elements":[]},{"c":110,"elements":[]},{"c":103,"elements":[]},{"c":46,"elements":[]},{"c":10,"elements":[]}],"StringContent":[{"s":"It's a living.\n","elements":[]}]}],"CurrentTextSegment":0},{"Identifier":"4","StartTime":54.198001861572269,"EndTime":57.74399948120117,"RegionFeature":"","CueElement":{"Name":"","Value":""},"TextSegments":[{"Content":[{"c":89,"elements":[]},{"c":111,"elements":[]},{"c":117,"elements":[]},{"c":32,"elements":[]},{"c":104,"elements":[]},{"c":97,"elements":[]},{"c":110,"elements":[]},{"c":100,"elements":[]},{"c":108,"elements":[]},{"c":101,"elements":[]},{"c":32,"elements":[]},{"c":106,"elements":[]},{"c":117,"elements":[]},{"c":115,"elements":[]},{"c":116,"elements":[]},{"c":32,"elements":[]},{"c":97,"elements":[]},{"c":117,"elements":[]},{"c":116,"elements":[]},{"c":111,"elements":[]},{"c":109,"elements":[]},{"c":111,"elements":[]},{"c":98,"elements":[]},{"c":105,"elements":[]},{"c":108,"elements":[]},{"c":101,"elements":[]},{"c":10,"elements":[]},{"c":105,"elements":[]},{"c":110,"elements":[]},{"c":115,"elements":[]},{"c":117,"elements":[]},{"c":114,"elements":[]},{"c":97,"elements":[]},{"c":110,"elements":[]},{"c":99,"elements":[]},{"c":101,"elements":[]},{"c":44,"elements":[]},{"c":32,"elements":[]},{"c":111,"elements":[]},{"c":114,"elements":[]},{"c":32,"elements":[]},{"c":97,"elements":[]},{"c":108,"elements":[]},{"c":108,"elements":[]},{"c":32,"elements":[]},{"c":107,"elements":[]},{"c":105,"elements":[]},{"c":110,"elements":[]},{"c":100,"elements":[]},{"c":115,"elements":[]},{"c":63,"elements":[]},{"c":10,"elements":[]}],"StringContent":[{"s":"You handle just automobile\ninsurance, or all kinds?\n","elements":[]}]}],"CurrentTextSegment":0},{"Identifier":"5","StartTime":57.82699966430664,"EndTime":59.48899841308594,"RegionFeature":"","CueElement":{"Name":"","Value":""},"TextSegments":[{"Content":[{"c":65,"elements":[]},{"c":108,"elements":[]},{"c":108,"elements":[]},{"c":32,"elements":[]},{"c":107,"elements":[]},{"c":105,"elements":[]},{"c":110,"elements":[]},{"c":100,"elements":[]},{"c":115,"elements":[]},{"c":46,"elements":[]},{"c":32,"elements":[]},{"c":70,"elements":[]},{"c":105,"elements":[]},{"c":114,"elements":[]},{"c":101,"elements":[]},{"c":44,"elements":[]},{"c":10,"elements":[]},{"c":101,"elements":[]},{"c":97,"elements":[]},{"c":114,"elements":[]},{"c":116,"elements":[]},{"c":104,"elements":[]},{"c":113,"elements":[]},{"c":117,"elements":[]},{"c":97,"elements":[]},{"c":107,"elements":[]},{"c":101,"elements":[]},{"c":44,"elements":[]},{"c":32,"elements":[]},{"c":116,"elements":[]},{"c":104,"elements":[]},{"c":101,"elements":[]},{"c":102,"elements":[]},{"c":116,"elements":[]},{"c":44,"elements":[]},{"c":10,"elements":[]}],"StringContent":[{"s":"All kinds. Fire,\nearthquake, theft,\n","elements":[]}]}],"CurrentTextSegment":0},{"Identifier":"6","StartTime":59.513999938964847,"EndTime":61.24700164794922,"RegionFeature":"","CueElement":{"Name":"","Value":""},"TextSegments":[{"Content":[{"c":112,"elements":[]},{"c":117,"elements":[]},{"c":98,"elements":[]},{"c":108,"elements":[]},{"c":105,"elements":[]},{"c":99,"elements":[]},{"c":32,"elements":[]},{"c":108,"elements":[]},{"c":105,"elements":[]},{"c":97,"elements":[]},{"c":98,"elements":[]},{"c":105,"elements":[]},{"c":108,"elements":[]},{"c":105,"elements":[]},{"c":116,"elements":[]},{"c":121,"elements":[]},{"c":44,"elements":[]},{"c":10,"elements":[]},{"c":103,"elements":[]},{"c":114,"elements":[]},{"c":111,"elements":[]},{"c":117,"elements":[]},{"c":112,"elements":[]},{"c":32,"elements":[]},{"c":105,"elements":[]},{"c":110,"elements":[]},{"c":115,"elements":[]},{"c":117,"elements":[]},{"c":114,"elements":[]},{"c":97,"elements":[]},{"c":110,"elements":[]},{"c":99,"elements":[]},{"c":101,"elements":[]},{"c":46,"elements":[]},{"c":46,"elements":[]},{"c":46,"elements":[]},{"c":10,"elements":[]}],"StringContent":[{"s":"public liability,\ngroup insurance...\n","elements":[]}]}],"CurrentTextSegment":0},{"Identifier":"7","StartTime":61.33100128173828,"EndTime":63.75,"RegionFeature":"","CueElement":{"Name":"","Value":""},"TextSegments":[{"Content":[{"c":105,"elements":[]},{"c":110,"elements":[]},{"c":100,"elements":[]},{"c":117,"elements":[]},{"c":115,"elements":[]},{"c":116,"elements":[]},{"c":114,"elements":[]},{"c":105,"elements":[]},{"c":97,"elements":[]},{"c":108,"elements":[]},{"c":32,"elements":[]},{"c":115,"elements":[]},{"c":116,"elements":[]},{"c":117,"elements":[]},{"c":102,"elements":[]},{"c":102,"elements":[]},{"c":32,"elements":[]},{"c":97,"elements":[]},{"c":110,"elements":[]},{"c":100,"elements":[]},{"c":32,"elements":[]},{"c":115,"elements":[]},{"c":111,"elements":[]},{"c":32,"elements":[]},{"c":111,"elements":[]},{"c":110,"elements":[]},{"c":44,"elements":[]},{"c":10,"elements":[]},{"c":114,"elements":[]},{"c":105,"elements":[]},{"c":103,"elements":[]},{"c":104,"elements":[]},{"c":116,"elements":[]},{"c":32,"elements":[]},{"c":100,"elements":[]},{"c":111,"elements":[]},{"c":119,"elements":[]},{"c":110,"elements":[]},{"c":32,"elements":[]},{"c":116,"elements":[]},{"c":104,"elements":[]},{"c":101,"elements":[]},{"c":32,"elements":[]},{"c":108,"elements":[]},{"c":105,"elements":[]},{"c":110,"elements":[]},{"c":101,"elements":[]},{"c":46,"elements":[]},{"c":10,"elements":[]}],"StringContent":[{"s":"industrial stuff and so on,\nright down the line.\n","elements":[]}]}],"CurrentTextSegment":0},{"Identifier":"8","StartTime":63.91699981689453,"EndTime":65.16799926757813,"RegionFeature":"","CueElement":{"Name":"","Value":""},"TextSegments":[{"Content":[{"c":65,"elements":[]},{"c":99,"elements":[]},{"c":99,"elements":[]},{"c":105,"elements":[]},{"c":100,"elements":[]},{"c":101,"elements":[]},{"c":110,"elements":[]},{"c":116,"elements":[]},{"c":32,"elements":[]},{"c":105,"elements":[]},{"c":110,"elements":[]},{"c":115,"elements":[]},{"c":117,"elements":[]},{"c":114,"elements":[]},{"c":97,"elements":[]},{"c":110,"elements":[]},{"c":99,"elements":[]},{"c":101,"elements":[]},{"c":63,"elements":[]},{"c":10,"elements":[]}],"StringContent":[{"s":"Accident insurance?\n","elements":[]}]}],"CurrentTextSegment":0},{"Identifier":"9","StartTime":65.2509994506836,"EndTime":67.46199798583985,"RegionFeature":"","CueElement":{"Name":"","Value":""},"TextSegments":[{"Content":[{"c":65,"elements":[]},{"c":99,"elements":[]},{"c":99,"elements":[]},{"c":105,"elements":[]},{"c":100,"elements":[]},{"c":101,"elements":[]},{"c":110,"elements":[]},{"c":116,"elements":[]},{"c":32,"elements":[]},{"c":105,"elements":[]},{"c":110,"elements":[]},{"c":115,"elements":[]},{"c":117,"elements":[]},{"c":114,"elements":[]},{"c":97,"elements":[]},{"c":110,"elements":[]},{"c":99,"elements":[]},{"c":101,"elements":[]},{"c":63,"elements":[]},{"c":10,"elements":[]},{"c":83,"elements":[]},{"c":117,"elements":[]},{"c":114,"elements":[]},{"c":101,"elements":[]},{"c":44,"elements":[]},{"c":32,"elements":[]},{"c":77,"elements":[]},{"c":114,"elements":[]},{"c":115,"elements":[]},{"c":46,"elements":[]},{"c":32,"elements":[]},{"c":68,"elements":[]},{"c":105,"elements":[]},{"c":101,"elements":[]},{"c":116,"elements":[]},{"c":114,"elements":[]},{"c":105,"elements":[]},{"c":99,"elements":[]},{"c":104,"elements":[]},{"c":115,"elements":[]},{"c":111,"elements":[]},{"c":110,"elements":[]},{"c":46,"elements":[]},{"c":10,"elements":[]}],"StringContent":[{"s":"Accident insurance?\nSure, Mrs. Dietrichson.\n","elements":[]}]}],"CurrentTextSegment":0},{"Identifier":"10","StartTime":69.4219970703125,"EndTime":72.59200286865235,"RegionFeature":"","CueElement":{"Name":"","Value":""},"TextSegments":[{"Content":[{"c":87,"elements":[]},{"c":105,"elements":[]},{"c":115,"elements":[]},{"c":104,"elements":[]},{"c":32,"elements":[]},{"c":121,"elements":[]},{"c":111,"elements":[]},{"c":117,"elements":[]},{"c":39,"elements":[]},{"c":100,"elements":[]},{"c":32,"elements":[]},{"c":116,"elements":[]},{"c":101,"elements":[]},{"c":108,"elements":[]},{"c":108,"elements":[]},{"c":32,"elements":[]},{"c":109,"elements":[]},{"c":101,"elements":[]},{"c":32,"elements":[]},{"c":119,"elements":[]},{"c":104,"elements":[]},{"c":97,"elements":[]},{"c":116,"elements":[]},{"c":39,"elements":[]},{"c":115,"elements":[]},{"c":10,"elements":[]},{"c":101,"elements":[]},{"c":110,"elements":[]},{"c":103,"elements":[]},{"c":114,"elements":[]},{"c":97,"elements":[]},{"c":118,"elements":[]},{"c":101,"elements":[]},{"c":100,"elements":[]},{"c":32,"elements":[]},{"c":111,"elements":[]},{"c":110,"elements":[]},{"c":32,"elements":[]},{"c":116,"elements":[]},{"c":104,"elements":[]},{"c":97,"elements":[]},{"c":116,"elements":[]},{"c":32,"elements":[]},{"c":97,"elements":[]},{"c":110,"elements":[]},{"c":107,"elements":[]},{"c":108,"elements":[]},{"c":101,"elements":[]},{"c":116,"elements":[]},{"c":46,"elements":[]},{"c":10,"elements":[]}],"StringContent":[{"s":"Wish you'd tell me what's\nengraved on that anklet.\n","elements":[]}]}],"CurrentTextSegment":0},{"Identifier":"11","StartTime":73.0510025024414,"EndTime":75.55400085449219,"RegionFeature":"","CueElement":{"Name":"","Value":""},"TextSegments":[{"Content":[{"c":74,"elements":[]},{"c":117,"elements":[]},{"c":115,"elements":[]},{"c":116,"elements":[]},{"c":32,"elements":[]},{"c":109,"elements":[]},{"c":121,"elements":[]},{"c":32,"elements":[]},{"c":110,"elements":[]},{"c":97,"elements":[]},{"c":109,"elements":[]},{"c":101,"elements":[]},{"c":46,"elements":[]},{"c":32,"elements":[]},{"c":65,"elements":[]},{"c":115,"elements":[]},{"c":44,"elements":[]},{"c":32,"elements":[]},{"c":102,"elements":[]},{"c":111,"elements":[]},{"c":114,"elements":[]},{"c":32,"elements":[]},{"c":105,"elements":[]},{"c":110,"elements":[]},{"c":115,"elements":[]},{"c":116,"elements":[]},{"c":97,"elements":[]},{"c":110,"elements":[]},{"c":99,"elements":[]},{"c":101,"elements":[]},{"c":63,"elements":[]},{"c":10,"elements":[]}],"StringContent":[{"s":"Just my name. As, for instance?\n","elements":[]}]}],"CurrentTextSegment":0},{"Identifier":"12","StartTime":77.13899993896485,"EndTime":78.88999938964844,"RegionFeature":"","CueElement":{"Name":"","Value":""},"TextSegments":[{"Content":[{"c":80,"elements":[]},{"c":104,"elements":[]},{"c":121,"elements":[]},{"c":108,"elements":[]},{"c":108,"elements":[]},{"c":105,"elements":[]},{"c":115,"elements":[]},{"c":46,"elements":[]},{"c":32,"elements":[]},{"c":80,"elements":[]},{"c":104,"elements":[]},{"c":121,"elements":[]},{"c":108,"elements":[]},{"c":108,"elements":[]},{"c":105,"elements":[]},{"c":115,"elements":[]},{"c":63,"elements":[]},{"c":10,"elements":[]}],"StringContent":[{"s":"Phyllis. Phyllis?\n","elements":[]}]}],"CurrentTextSegment":0},{"Identifier":"13","StartTime":79.55799865722656,"EndTime":82.35199737548828,"RegionFeature":"","CueElement":{"Name":"","Value":""},"TextSegments":[{"Content":[{"c":73,"elements":[]},{"c":32,"elements":[]},{"c":116,"elements":[]},{"c":104,"elements":[]},{"c":105,"elements":[]},{"c":110,"elements":[]},{"c":107,"elements":[]},{"c":32,"elements":[]},{"c":73,"elements":[]},{"c":32,"elements":[]},{"c":108,"elements":[]},{"c":105,"elements":[]},{"c":107,"elements":[]},{"c":101,"elements":[]},{"c":32,"elements":[]},{"c":116,"elements":[]},{"c":104,"elements":[]},{"c":97,"elements":[]},{"c":116,"elements":[]},{"c":46,"elements":[]},{"c":10,"elements":[]},{"c":66,"elements":[]},{"c":117,"elements":[]},{"c":116,"elements":[]},{"c":32,"elements":[]},{"c":121,"elements":[]},{"c":111,"elements":[]},{"c":117,"elements":[]},{"c":39,"elements":[]},{"c":114,"elements":[]},{"c":101,"elements":[]},{"c":32,"elements":[]},{"c":110,"elements":[]},{"c":111,"elements":[]},{"c":116,"elements":[]},{"c":32,"elements":[]},{"c":115,"elements":[]},{"c":117,"elements":[]},{"c":114,"elements":[]},{"c":101,"elements":[]},{"c":63,"elements":[]},{"c":10,"elements":[]}],"StringContent":[{"s":"I think I like that.\nBut you're not sure?\n","elements":[]}]}],"CurrentTextSegment":0},{"Identifier":"14","StartTime":82.43599700927735,"EndTime":85.56400299072266,"RegionFeature":"","CueElement":{"Name":"","Value":""},"TextSegments":[{"Content":[{"c":73,"elements":[]},{"c":39,"elements":[]},{"c":100,"elements":[]},{"c":32,"elements":[]},{"c":104,"elements":[]},{"c":97,"elements":[]},{"c":118,"elements":[]},{"c":101,"elements":[]},{"c":32,"elements":[]},{"c":116,"elements":[]},{"c":111,"elements":[]},{"c":32,"elements":[]},{"c":100,"elements":[]},{"c":114,"elements":[]},{"c":105,"elements":[]},{"c":118,"elements":[]},{"c":101,"elements":[]},{"c":32,"elements":[]},{"c":105,"elements":[]},{"c":116,"elements":[]},{"c":32,"elements":[]},{"c":97,"elements":[]},{"c":114,"elements":[]},{"c":111,"elements":[]},{"c":117,"elements":[]},{"c":110,"elements":[]},{"c":100,"elements":[]},{"c":10,"elements":[]},{"c":116,"elements":[]},{"c":104,"elements":[]},{"c":101,"elements":[]},{"c":32,"elements":[]},{"c":98,"elements":[]},{"c":108,"elements":[]},{"c":111,"elements":[]},{"c":99,"elements":[]},{"c":107,"elements":[]},{"c":32,"elements":[]},{"c":97,"elements":[]},{"c":32,"elements":[]},{"c":99,"elements":[]},{"c":111,"elements":[]},{"c":117,"elements":[]},{"c":112,"elements":[]},{"c":108,"elements":[]},{"c":101,"elements":[]},{"c":32,"elements":[]},{"c":111,"elements":[]},{"c":102,"elements":[]},{"c":32,"elements":[]},{"c":116,"elements":[]},{"c":105,"elements":[]},{"c":109,"elements":[]},{"c":101,"elements":[]},{"c":115,"elements":[]},{"c":46,"elements":[]},{"c":10,"elements":[]}],"StringContent":[{"s":"I'd have to drive it around\nthe block a couple of times.\n","elements":[]}]}],"CurrentTextSegment":0},{"Identifier":"15","StartTime":85.64700317382813,"EndTime":88.4000015258789,"RegionFeature":"","CueElement":{"Name":"","Value":""},"TextSegments":[{"Content":[{"c":77,"elements":[]},{"c":114,"elements":[]},{"c":46,"elements":[]},{"c":32,"elements":[]},{"c":78,"elements":[]},{"c":101,"elements":[]},{"c":102,"elements":[]},{"c":102,"elements":[]},{"c":44,"elements":[]},{"c":32,"elements":[]},{"c":119,"elements":[]},{"c":104,"elements":[]},{"c":121,"elements":[]},{"c":32,"elements":[]},{"c":100,"elements":[]},{"c":111,"elements":[]},{"c":110,"elements":[]},{"c":39,"elements":[]},{"c":116,"elements":[]},{"c":32,"elements":[]},{"c":121,"elements":[]},{"c":111,"elements":[]},{"c":117,"elements":[]},{"c":32,"elements":[]},{"c":100,"elements":[]},{"c":114,"elements":[]},{"c":111,"elements":[]},{"c":112,"elements":[]},{"c":10,"elements":[]},{"c":98,"elements":[]},{"c":121,"elements":[]},{"c":32,"elements":[]},{"c":116,"elements":[]},{"c":111,"elements":[]},{"c":109,"elements":[]},{"c":111,"elements":[]},{"c":114,"elements":[]},{"c":114,"elements":[]},{"c":111,"elements":[]},{"c":119,"elements":[]},{"c":32,"elements":[]},{"c":101,"elements":[]},{"c":118,"elements":[]},{"c":101,"elements":[]},{"c":110,"elements":[]},{"c":105,"elements":[]},{"c":110,"elements":[]},{"c":103,"elements":[]},{"c":32,"elements":[]},{"c":97,"elements":[]},{"c":114,"elements":[]},{"c":111,"elements":[]},{"c":117,"elements":[]},{"c":110,"elements":[]},{"c":100,"elements":[]},{"c":32,"elements":[]},{"c":56,"elements":[]},{"c":58,"elements":[]},{"c":51,"elements":[]},{"c":48,"elements":[]},{"c":63,"elements":[]},{"c":10,"elements":[]}],"StringContent":[{"s":"Mr. Neff, why don't you drop\nby tomorrow evening around 8:30?\n","elements":[]}]}],"CurrentTextSegment":0},{"Identifier":"16","StartTime":88.44200134277344,"EndTime":90.31900024414063,"RegionFeature":"","CueElement":{"Name":"","Value":""},"TextSegments":[{"Content":[{"c":72,"elements":[]},{"c":101,"elements":[]},{"c":39,"elements":[]},{"c":108,"elements":[]},{"c":108,"elements":[]},{"c":32,"elements":[]},{"c":98,"elements":[]},{"c":101,"elements":[]},{"c":32,"elements":[]},{"c":105,"elements":[]},{"c":110,"elements":[]},{"c":32,"elements":[]},{"c":116,"elements":[]},{"c":104,"elements":[]},{"c":101,"elements":[]},{"c":110,"elements":[]},{"c":46,"elements":[]},{"c":32,"elements":[]},{"c":87,"elements":[]},{"c":104,"elements":[]},{"c":111,"elements":[]},{"c":63,"elements":[]},{"c":10,"elements":[]}],"StringContent":[{"s":"He'll be in then. Who?\n","elements":[]}]}],"CurrentTextSegment":0},{"Identifier":"17","StartTime":90.4020004272461,"EndTime":93.61399841308594,"RegionFeature":"","CueElement":{"Name":"","Value":""},"TextSegments":[{"Content":[{"c":77,"elements":[]},{"c":121,"elements":[]},{"c":32,"elements":[]},{"c":104,"elements":[]},{"c":117,"elements":[]},{"c":115,"elements":[]},{"c":98,"elements":[]},{"c":97,"elements":[]},{"c":110,"elements":[]},{"c":100,"elements":[]},{"c":46,"elements":[]},{"c":32,"elements":[]},{"c":89,"elements":[]},{"c":111,"elements":[]},{"c":117,"elements":[]},{"c":32,"elements":[]},{"c":119,"elements":[]},{"c":101,"elements":[]},{"c":114,"elements":[]},{"c":101,"elements":[]},{"c":32,"elements":[]},{"c":97,"elements":[]},{"c":110,"elements":[]},{"c":120,"elements":[]},{"c":105,"elements":[]},{"c":111,"elements":[]},{"c":117,"elements":[]},{"c":115,"elements":[]},{"c":10,"elements":[]},{"c":116,"elements":[]},{"c":111,"elements":[]},{"c":32,"elements":[]},{"c":116,"elements":[]},{"c":97,"elements":[]},{"c":108,"elements":[]},{"c":107,"elements":[]},{"c":32,"elements":[]},{"c":116,"elements":[]},{"c":111,"elements":[]},{"c":32,"elements":[]},{"c":104,"elements":[]},{"c":105,"elements":[]},{"c":109,"elements":[]},{"c":44,"elements":[]},{"c":32,"elements":[]},{"c":119,"elements":[]},{"c":101,"elements":[]},{"c":114,"elements":[]},{"c":101,"elements":[]},{"c":110,"elements":[]},{"c":39,"elements":[]},{"c":116,"elements":[]},{"c":32,"elements":[]},{"c":121,"elements":[]},{"c":111,"elements":[]},{"c":117,"elements":[]},{"c":63,"elements":[]},{"c":10,"elements":[]}],"StringContent":[{"s":"My husband. You were anxious\nto talk to him, weren't you?\n","elements":[]}]}],"CurrentTextSegment":0},{"Identifier":"18","StartTime":93.6969985961914,"EndTime":96.61699676513672,"RegionFeature":"","CueElement":{"Name":"","Value":""},"TextSegments":[{"Content":[{"c":89,"elements":[]},{"c":101,"elements":[]},{"c":97,"elements":[]},{"c":104,"elements":[]},{"c":44,"elements":[]},{"c":32,"elements":[]},{"c":73,"elements":[]},{"c":32,"elements":[]},{"c":119,"elements":[]},{"c":97,"elements":[]},{"c":115,"elements":[]},{"c":44,"elements":[]},{"c":32,"elements":[]},{"c":98,"elements":[]},{"c":117,"elements":[]},{"c":116,"elements":[]},{"c":32,"elements":[]},{"c":73,"elements":[]},{"c":39,"elements":[]},{"c":109,"elements":[]},{"c":32,"elements":[]},{"c":115,"elements":[]},{"c":111,"elements":[]},{"c":114,"elements":[]},{"c":116,"elements":[]},{"c":32,"elements":[]},{"c":111,"elements":[]},{"c":102,"elements":[]},{"c":10,"elements":[]},{"c":103,"elements":[]},{"c":101,"elements":[]},{"c":116,"elements":[]},{"c":116,"elements":[]},{"c":105,"elements":[]},{"c":110,"elements":[]},{"c":103,"elements":[]},{"c":32,"elements":[]},{"c":111,"elements":[]},{"c":118,"elements":[]},{"c":101,"elements":[]},{"c":114,"elements":[]},{"c":32,"elements":[]},{"c":116,"elements":[]},{"c":104,"elements":[]},{"c":101,"elements":[]},{"c":32,"elements":[]},{"c":105,"elements":[]},{"c":100,"elements":[]},{"c":101,"elements":[]},{"c":97,"elements":[]},{"c":46,"elements":[]},{"c":46,"elements":[]},{"c":46,"elements":[]},{"c":10,"elements":[]}],"StringContent":[{"s":"Yeah, I was, but I'm sort of\ngetting over the idea...\n","elements":[]}]}],"CurrentTextSegment":0},{"Identifier":"19","StartTime":96.65899658203125,"EndTime":98.03500366210938,"RegionFeature":"","CueElement":{"Name":"","Value":""},"TextSegments":[{"Content":[{"c":105,"elements":[]},{"c":102,"elements":[]},{"c":32,"elements":[]},{"c":121,"elements":[]},{"c":111,"elements":[]},{"c":117,"elements":[]},{"c":32,"elements":[]},{"c":107,"elements":[]},{"c":110,"elements":[]},{"c":111,"elements":[]},{"c":119,"elements":[]},{"c":32,"elements":[]},{"c":119,"elements":[]},{"c":104,"elements":[]},{"c":97,"elements":[]},{"c":116,"elements":[]},{"c":32,"elements":[]},{"c":73,"elements":[]},{"c":32,"elements":[]},{"c":109,"elements":[]},{"c":101,"elements":[]},{"c":97,"elements":[]},{"c":110,"elements":[]},{"c":46,"elements":[]},{"c":10,"elements":[]}],"StringContent":[{"s":"if you know what I mean.\n","elements":[]}]}],"CurrentTextSegment":0},{"Identifier":"20","StartTime":98.11900329589844,"EndTime":101.53900146484375,"RegionFeature":"","CueElement":{"Name":"","Value":""},"TextSegments":[{"Content":[{"c":84,"elements":[]},{"c":104,"elements":[]},{"c":101,"elements":[]},{"c":114,"elements":[]},{"c":101,"elements":[]},{"c":39,"elements":[]},{"c":115,"elements":[]},{"c":32,"elements":[]},{"c":97,"elements":[]},{"c":32,"elements":[]},{"c":115,"elements":[]},{"c":112,"elements":[]},{"c":101,"elements":[]},{"c":101,"elements":[]},{"c":100,"elements":[]},{"c":32,"elements":[]},{"c":108,"elements":[]},{"c":105,"elements":[]},{"c":109,"elements":[]},{"c":105,"elements":[]},{"c":116,"elements":[]},{"c":32,"elements":[]},{"c":105,"elements":[]},{"c":110,"elements":[]},{"c":32,"elements":[]},{"c":116,"elements":[]},{"c":104,"elements":[]},{"c":105,"elements":[]},{"c":115,"elements":[]},{"c":10,"elements":[]},{"c":115,"elements":[]},{"c":116,"elements":[]},{"c":97,"elements":[]},{"c":116,"elements":[]},{"c":101,"elements":[]},{"c":44,"elements":[]},{"c":32,"elements":[]},{"c":77,"elements":[]},{"c":114,"elements":[]},{"c":46,"elements":[]},{"c":32,"elements":[]},{"c":78,"elements":[]},{"c":101,"elements":[]},{"c":102,"elements":[]},{"c":102,"elements":[]},{"c":46,"elements":[]},{"c":32,"elements":[]},{"c":52,"elements":[]},{"c":53,"elements":[]},{"c":32,"elements":[]},{"c":109,"elements":[]},{"c":105,"elements":[]},{"c":108,"elements":[]},{"c":101,"elements":[]},{"c":115,"elements":[]},{"c":32,"elements":[]},{"c":97,"elements":[]},{"c":110,"elements":[]},{"c":32,"elements":[]},{"c":104,"elements":[]},{"c":111,"elements":[]},{"c":117,"elements":[]},{"c":114,"elements":[]},{"c":46,"elements":[]},{"c":10,"elements":[]}],"StringContent":[{"s":"There's a speed limit in this\nstate, Mr. Neff. 45 miles an hour.\n","elements":[]}]}],"CurrentTextSegment":0},{"Identifier":"21","StartTime":101.62200164794922,"EndTime":104.875,"RegionFeature":"","CueElement":{"Name":"","Value":""},"TextSegments":[{"Content":[{"c":72,"elements":[]},{"c":111,"elements":[]},{"c":119,"elements":[]},{"c":32,"elements":[]},{"c":102,"elements":[]},{"c":97,"elements":[]},{"c":115,"elements":[]},{"c":116,"elements":[]},{"c":32,"elements":[]},{"c":119,"elements":[]},{"c":97,"elements":[]},{"c":115,"elements":[]},{"c":32,"elements":[]},{"c":73,"elements":[]},{"c":32,"elements":[]},{"c":103,"elements":[]},{"c":111,"elements":[]},{"c":105,"elements":[]},{"c":110,"elements":[]},{"c":103,"elements":[]},{"c":44,"elements":[]},{"c":32,"elements":[]},{"c":111,"elements":[]},{"c":102,"elements":[]},{"c":102,"elements":[]},{"c":105,"elements":[]},{"c":99,"elements":[]},{"c":101,"elements":[]},{"c":114,"elements":[]},{"c":63,"elements":[]},{"c":10,"elements":[]},{"c":73,"elements":[]},{"c":39,"elements":[]},{"c":100,"elements":[]},{"c":32,"elements":[]},{"c":115,"elements":[]},{"c":97,"elements":[]},{"c":121,"elements":[]},{"c":32,"elements":[]},{"c":97,"elements":[]},{"c":114,"elements":[]},{"c":111,"elements":[]},{"c":117,"elements":[]},{"c":110,"elements":[]},{"c":100,"elements":[]},{"c":32,"elements":[]},{"c":57,"elements":[]},{"c":48,"elements":[]},{"c":46,"elements":[]},{"c":10,"elements":[]}],"StringContent":[{"s":"How fast was I going, officer?\nI'd say around 90.\n","elements":[]}]}],"CurrentTextSegment":0},{"Identifier":"22","StartTime":105.16699981689453,"EndTime":107.60700225830078,"RegionFeature":"","CueElement":{"Name":"","Value":""},"TextSegments":[{"Content":[{"c":83,"elements":[]},{"c":117,"elements":[]},{"c":112,"elements":[]},{"c":112,"elements":[]},{"c":111,"elements":[]},{"c":115,"elements":[]},{"c":101,"elements":[]},{"c":32,"elements":[]},{"c":121,"elements":[]},{"c":111,"elements":[]},{"c":117,"elements":[]},{"c":32,"elements":[]},{"c":103,"elements":[]},{"c":101,"elements":[]},{"c":116,"elements":[]},{"c":32,"elements":[]},{"c":100,"elements":[]},{"c":111,"elements":[]},{"c":119,"elements":[]},{"c":110,"elements":[]},{"c":32,"elements":[]},{"c":111,"elements":[]},{"c":102,"elements":[]},{"c":102,"elements":[]},{"c":32,"elements":[]},{"c":121,"elements":[]},{"c":111,"elements":[]},{"c":117,"elements":[]},{"c":114,"elements":[]},{"c":10,"elements":[]},{"c":109,"elements":[]},{"c":111,"elements":[]},{"c":116,"elements":[]},{"c":111,"elements":[]},{"c":114,"elements":[]},{"c":99,"elements":[]},{"c":121,"elements":[]},{"c":99,"elements":[]},{"c":108,"elements":[]},{"c":101,"elements":[]},{"c":32,"elements":[]},{"c":97,"elements":[]},{"c":110,"elements":[]},{"c":100,"elements":[]},{"c":32,"elements":[]},{"c":103,"elements":[]},{"c":105,"elements":[]},{"c":118,"elements":[]},{"c":101,"elements":[]},{"c":32,"elements":[]},{"c":109,"elements":[]},{"c":101,"elements":[]},{"c":32,"elements":[]},{"c":97,"elements":[]},{"c":32,"elements":[]},{"c":116,"elements":[]},{"c":105,"elements":[]},{"c":99,"elements":[]},{"c":107,"elements":[]},{"c":101,"elements":[]},{"c":116,"elements":[]},{"c":46,"elements":[]},{"c":10,"elements":[]}],"StringContent":[{"s":"Suppose you get down off your\nmotorcycle and give me a ticket.\n","elements":[]}]}],"CurrentTextSegment":0},{"Identifier":"23","StartTime":107.62799835205078,"EndTime":109.88099670410156,"RegionFeature":"","CueElement":{"Name":"","Value":""},"TextSegments":[{"Content":[{"c":83,"elements":[]},{"c":117,"elements":[]},{"c":112,"elements":[]},{"c":112,"elements":[]},{"c":111,"elements":[]},{"c":115,"elements":[]},{"c":101,"elements":[]},{"c":32,"elements":[]},{"c":73,"elements":[]},{"c":32,"elements":[]},{"c":108,"elements":[]},{"c":101,"elements":[]},{"c":116,"elements":[]},{"c":32,"elements":[]},{"c":121,"elements":[]},{"c":111,"elements":[]},{"c":117,"elements":[]},{"c":32,"elements":[]},{"c":111,"elements":[]},{"c":102,"elements":[]},{"c":102,"elements":[]},{"c":10,"elements":[]},{"c":119,"elements":[]},{"c":105,"elements":[]},{"c":116,"elements":[]},{"c":104,"elements":[]},{"c":32,"elements":[]},{"c":97,"elements":[]},{"c":32,"elements":[]},{"c":119,"elements":[]},{"c":97,"elements":[]},{"c":114,"elements":[]},{"c":110,"elements":[]},{"c":105,"elements":[]},{"c":110,"elements":[]},{"c":103,"elements":[]},{"c":32,"elements":[]},{"c":116,"elements":[]},{"c":104,"elements":[]},{"c":105,"elements":[]},{"c":115,"elements":[]},{"c":32,"elements":[]},{"c":116,"elements":[]},{"c":105,"elements":[]},{"c":109,"elements":[]},{"c":101,"elements":[]},{"c":46,"elements":[]},{"c":10,"elements":[]}],"StringContent":[{"s":"Suppose I let you off\nwith a warning this time.\n","elements":[]}]}],"CurrentTextSegment":0},{"Identifier":"24","StartTime":109.96399688720703,"EndTime":111.67400360107422,"RegionFeature":"","CueElement":{"Name":"","Value":""},"TextSegments":[{"Content":[{"c":83,"elements":[]},{"c":117,"elements":[]},{"c":112,"elements":[]},{"c":112,"elements":[]},{"c":111,"elements":[]},{"c":115,"elements":[]},{"c":101,"elements":[]},{"c":32,"elements":[]},{"c":105,"elements":[]},{"c":116,"elements":[]},{"c":32,"elements":[]},{"c":100,"elements":[]},{"c":111,"elements":[]},{"c":101,"elements":[]},{"c":115,"elements":[]},{"c":110,"elements":[]},{"c":39,"elements":[]},{"c":116,"elements":[]},{"c":32,"elements":[]},{"c":116,"elements":[]},{"c":97,"elements":[]},{"c":107,"elements":[]},{"c":101,"elements":[]},{"c":46,"elements":[]},{"c":10,"elements":[]}],"StringContent":[{"s":"Suppose it doesn't take.\n","elements":[]}]}],"CurrentTextSegment":0},{"Identifier":"25","StartTime":111.75800323486328,"EndTime":114.13500213623047,"RegionFeature":"","CueElement":{"Name":"","Value":""},"TextSegments":[{"Content":[{"c":83,"elements":[]},{"c":117,"elements":[]},{"c":112,"elements":[]},{"c":112,"elements":[]},{"c":111,"elements":[]},{"c":115,"elements":[]},{"c":101,"elements":[]},{"c":32,"elements":[]},{"c":73,"elements":[]},{"c":32,"elements":[]},{"c":104,"elements":[]},{"c":97,"elements":[]},{"c":118,"elements":[]},{"c":101,"elements":[]},{"c":32,"elements":[]},{"c":116,"elements":[]},{"c":111,"elements":[]},{"c":32,"elements":[]},{"c":119,"elements":[]},{"c":104,"elements":[]},{"c":97,"elements":[]},{"c":99,"elements":[]},{"c":107,"elements":[]},{"c":32,"elements":[]},{"c":121,"elements":[]},{"c":111,"elements":[]},{"c":117,"elements":[]},{"c":10,"elements":[]},{"c":111,"elements":[]},{"c":118,"elements":[]},{"c":101,"elements":[]},{"c":114,"elements":[]},{"c":32,"elements":[]},{"c":116,"elements":[]},{"c":104,"elements":[]},{"c":101,"elements":[]},{"c":32,"elements":[]},{"c":107,"elements":[]},{"c":110,"elements":[]},{"c":117,"elements":[]},{"c":99,"elements":[]},{"c":107,"elements":[]},{"c":108,"elements":[]},{"c":101,"elements":[]},{"c":115,"elements":[]},{"c":46,"elements":[]},{"c":10,"elements":[]}],"StringContent":[{"s":"Suppose I have to whack you\nover the knuckles.\n","elements":[]}]}],"CurrentTextSegment":0},{"Identifier":"26","StartTime":114.177001953125,"EndTime":117.09600067138672,"RegionFeature":"","CueElement":{"Name":"","Value":""},"TextSegments":[{"Content":[{"c":83,"elements":[]},{"c":117,"elements":[]},{"c":112,"elements":[]},{"c":112,"elements":[]},{"c":111,"elements":[]},{"c":115,"elements":[]},{"c":101,"elements":[]},{"c":32,"elements":[]},{"c":73,"elements":[]},{"c":32,"elements":[]},{"c":98,"elements":[]},{"c":117,"elements":[]},{"c":115,"elements":[]},{"c":116,"elements":[]},{"c":32,"elements":[]},{"c":111,"elements":[]},{"c":117,"elements":[]},{"c":116,"elements":[]},{"c":32,"elements":[]},{"c":99,"elements":[]},{"c":114,"elements":[]},{"c":121,"elements":[]},{"c":105,"elements":[]},{"c":110,"elements":[]},{"c":103,"elements":[]},{"c":32,"elements":[]},{"c":97,"elements":[]},{"c":110,"elements":[]},{"c":100,"elements":[]},{"c":10,"elements":[]},{"c":112,"elements":[]},{"c":117,"elements":[]},{"c":116,"elements":[]},{"c":32,"elements":[]},{"c":109,"elements":[]},{"c":121,"elements":[]},{"c":32,"elements":[]},{"c":104,"elements":[]},{"c":101,"elements":[]},{"c":97,"elements":[]},{"c":100,"elements":[]},{"c":32,"elements":[]},{"c":111,"elements":[]},{"c":110,"elements":[]},{"c":32,"elements":[]},{"c":121,"elements":[]},{"c":111,"elements":[]},{"c":117,"elements":[]},{"c":114,"elements":[]},{"c":32,"elements":[]},{"c":115,"elements":[]},{"c":104,"elements":[]},{"c":111,"elements":[]},{"c":117,"elements":[]},{"c":108,"elements":[]},{"c":100,"elements":[]},{"c":101,"elements":[]},{"c":114,"elements":[]},{"c":46,"elements":[]},{"c":10,"elements":[]}],"StringContent":[{"s":"Suppose I bust out crying and\nput my head on your shoulder.\n","elements":[]}]}],"CurrentTextSegment":0},{"Identifier":"27","StartTime":117.13800048828125,"EndTime":120.26599884033203,"RegionFeature":"","CueElement":{"Name":"","Value":""},"TextSegments":[{"Content":[{"c":83,"elements":[]},{"c":117,"elements":[]},{"c":112,"elements":[]},{"c":112,"elements":[]},{"c":111,"elements":[]},{"c":115,"elements":[]},{"c":101,"elements":[]},{"c":32,"elements":[]},{"c":121,"elements":[]},{"c":111,"elements":[]},{"c":117,"elements":[]},{"c":32,"elements":[]},{"c":116,"elements":[]},{"c":114,"elements":[]},{"c":121,"elements":[]},{"c":32,"elements":[]},{"c":112,"elements":[]},{"c":117,"elements":[]},{"c":116,"elements":[]},{"c":116,"elements":[]},{"c":105,"elements":[]},{"c":110,"elements":[]},{"c":103,"elements":[]},{"c":32,"elements":[]},{"c":105,"elements":[]},{"c":116,"elements":[]},{"c":10,"elements":[]},{"c":111,"elements":[]},{"c":110,"elements":[]},{"c":32,"elements":[]},{"c":109,"elements":[]},{"c":121,"elements":[]},{"c":32,"elements":[]},{"c":104,"elements":[]},{"c":117,"elements":[]},{"c":115,"elements":[]},{"c":98,"elements":[]},{"c":97,"elements":[]},{"c":110,"elements":[]},{"c":100,"elements":[]},{"c":39,"elements":[]},{"c":115,"elements":[]},{"c":32,"elements":[]},{"c":115,"elements":[]},{"c":104,"elements":[]},{"c":111,"elements":[]},{"c":117,"elements":[]},{"c":108,"elements":[]},{"c":100,"elements":[]},{"c":101,"elements":[]},{"c":114,"elements":[]},{"c":46,"elements":[]},{"c":10,"elements":[]}],"StringContent":[{"s":"Suppose you try putting it\non my husband's shoulder.\n","elements":[]}]}],"CurrentTextSegment":0},{"Identifier":"28","StartTime":120.3499984741211,"EndTime":121.85099792480469,"RegionFeature":"","CueElement":{"Name":"","Value":""},"TextSegments":[{"Content":[{"c":84,"elements":[]},{"c":104,"elements":[]},{"c":97,"elements":[]},{"c":116,"elements":[]},{"c":32,"elements":[]},{"c":116,"elements":[]},{"c":101,"elements":[]},{"c":97,"elements":[]},{"c":114,"elements":[]},{"c":115,"elements":[]},{"c":32,"elements":[]},{"c":105,"elements":[]},{"c":116,"elements":[]},{"c":46,"elements":[]},{"c":10,"elements":[]}],"StringContent":[{"s":"That tears it.\n","elements":[]}]}],"CurrentTextSegment":0},{"Identifier":"29","StartTime":126.14700317382813,"EndTime":129.5260009765625,"RegionFeature":"","CueElement":{"Name":"","Value":""},"TextSegments":[{"Content":[{"c":56,"elements":[]},{"c":58,"elements":[]},{"c":51,"elements":[]},{"c":48,"elements":[]},{"c":32,"elements":[]},{"c":116,"elements":[]},{"c":111,"elements":[]},{"c":109,"elements":[]},{"c":111,"elements":[]},{"c":114,"elements":[]},{"c":114,"elements":[]},{"c":111,"elements":[]},{"c":119,"elements":[]},{"c":32,"elements":[]},{"c":101,"elements":[]},{"c":118,"elements":[]},{"c":101,"elements":[]},{"c":110,"elements":[]},{"c":105,"elements":[]},{"c":110,"elements":[]},{"c":103,"elements":[]},{"c":32,"elements":[]},{"c":116,"elements":[]},{"c":104,"elements":[]},{"c":101,"elements":[]},{"c":110,"elements":[]},{"c":46,"elements":[]},{"c":10,"elements":[]},{"c":84,"elements":[]},{"c":104,"elements":[]},{"c":97,"elements":[]},{"c":116,"elements":[]},{"c":39,"elements":[]},{"c":115,"elements":[]},{"c":32,"elements":[]},{"c":119,"elements":[]},{"c":104,"elements":[]},{"c":97,"elements":[]},{"c":116,"elements":[]},{"c":32,"elements":[]},{"c":73,"elements":[]},{"c":32,"elements":[]},{"c":115,"elements":[]},{"c":117,"elements":[]},{"c":103,"elements":[]},{"c":103,"elements":[]},{"c":101,"elements":[]},{"c":115,"elements":[]},{"c":116,"elements":[]},{"c":101,"elements":[]},{"c":100,"elements":[]},{"c":46,"elements":[]},{"c":10,"elements":[]}],"StringContent":[{"s":"8:30 tomorrow evening then.\nThat's what I suggested.\n","elements":[]}]}],"CurrentTextSegment":0},{"Identifier":"30","StartTime":129.60899353027345,"EndTime":132.2790069580078,"RegionFeature":"","CueElement":{"Name":"","Value":""},"TextSegments":[{"Content":[{"c":87,"elements":[]},{"c":105,"elements":[]},{"c":108,"elements":[]},{"c":108,"elements":[]},{"c":32,"elements":[]},{"c":121,"elements":[]},{"c":111,"elements":[]},{"c":117,"elements":[]},{"c":32,"elements":[]},{"c":98,"elements":[]},{"c":101,"elements":[]},{"c":32,"elements":[]},{"c":104,"elements":[]},{"c":101,"elements":[]},{"c":114,"elements":[]},{"c":101,"elements":[]},{"c":44,"elements":[]},{"c":32,"elements":[]},{"c":116,"elements":[]},{"c":111,"elements":[]},{"c":111,"elements":[]},{"c":63,"elements":[]},{"c":10,"elements":[]},{"c":73,"elements":[]},{"c":32,"elements":[]},{"c":103,"elements":[]},{"c":117,"elements":[]},{"c":101,"elements":[]},{"c":115,"elements":[]},{"c":115,"elements":[]},{"c":32,"elements":[]},{"c":115,"elements":[]},{"c":111,"elements":[]},{"c":44,"elements":[]},{"c":32,"elements":[]},{"c":73,"elements":[]},{"c":32,"elements":[]},{"c":117,"elements":[]},{"c":115,"elements":[]},{"c":117,"elements":[]},{"c":97,"elements":[]},{"c":108,"elements":[]},{"c":108,"elements":[]},{"c":121,"elements":[]},{"c":32,"elements":[]},{"c":97,"elements":[]},{"c":109,"elements":[]},{"c":46,"elements":[]},{"c":10,"elements":[]}],"StringContent":[{"s":"Will you be here, too?\nI guess so, I usually am.\n","elements":[]}]}],"CurrentTextSegment":0},{"Identifier":"31","StartTime":132.36199951171876,"EndTime":134.656005859375,"RegionFeature":"","CueElement":{"Name":"","Value":""},"TextSegments":[{"Content":[{"c":83,"elements":[]},{"c":97,"elements":[]},{"c":109,"elements":[]},{"c":101,"elements":[]},{"c":32,"elements":[]},{"c":99,"elements":[]},{"c":104,"elements":[]},{"c":97,"elements":[]},{"c":105,"elements":[]},{"c":114,"elements":[]},{"c":44,"elements":[]},{"c":32,"elements":[]},{"c":115,"elements":[]},{"c":97,"elements":[]},{"c":109,"elements":[]},{"c":101,"elements":[]},{"c":32,"elements":[]},{"c":112,"elements":[]},{"c":101,"elements":[]},{"c":114,"elements":[]},{"c":102,"elements":[]},{"c":117,"elements":[]},{"c":109,"elements":[]},{"c":101,"elements":[]},{"c":44,"elements":[]},{"c":10,"elements":[]},{"c":115,"elements":[]},{"c":97,"elements":[]},{"c":109,"elements":[]},{"c":101,"elements":[]},{"c":32,"elements":[]},{"c":97,"elements":[]},{"c":110,"elements":[]},{"c":107,"elements":[]},{"c":108,"elements":[]},{"c":101,"elements":[]},{"c":116,"elements":[]},{"c":63,"elements":[]},{"c":10,"elements":[]}],"StringContent":[{"s":"Same chair, same perfume,\nsame anklet?\n","elements":[]}]}],"CurrentTextSegment":0},{"Identifier":"32","StartTime":134.74000549316407,"EndTime":136.7830047607422,"RegionFeature":"","CueElement":{"Name":"","Value":""},"TextSegments":[{"Content":[{"c":73,"elements":[]},{"c":32,"elements":[]},{"c":119,"elements":[]},{"c":111,"elements":[]},{"c":110,"elements":[]},{"c":100,"elements":[]},{"c":101,"elements":[]},{"c":114,"elements":[]},{"c":32,"elements":[]},{"c":105,"elements":[]},{"c":102,"elements":[]},{"c":32,"elements":[]},{"c":73,"elements":[]},{"c":32,"elements":[]},{"c":107,"elements":[]},{"c":110,"elements":[]},{"c":111,"elements":[]},{"c":119,"elements":[]},{"c":10,"elements":[]},{"c":119,"elements":[]},{"c":104,"elements":[]},{"c":97,"elements":[]},{"c":116,"elements":[]},{"c":32,"elements":[]},{"c":121,"elements":[]},{"c":111,"elements":[]},{"c":117,"elements":[]},{"c":32,"elements":[]},{"c":109,"elements":[]},{"c":101,"elements":[]},{"c":97,"elements":[]},{"c":110,"elements":[]},{"c":46,"elements":[]},{"c":10,"elements":[]}],"StringContent":[{"s":"I wonder if I know\nwhat you mean.\n","elements":[]}]}],"CurrentTextSegment":0},{"Identifier":"33","StartTime":137.78399658203126,"EndTime":139.66099548339845,"RegionFeature":"","CueElement":{"Name":"","Value":""},"TextSegments":[{"Content":[{"c":73,"elements":[]},{"c":32,"elements":[]},{"c":119,"elements":[]},{"c":111,"elements":[]},{"c":110,"elements":[]},{"c":100,"elements":[]},{"c":101,"elements":[]},{"c":114,"elements":[]},{"c":32,"elements":[]},{"c":105,"elements":[]},{"c":102,"elements":[]},{"c":32,"elements":[]},{"c":121,"elements":[]},{"c":111,"elements":[]},{"c":117,"elements":[]},{"c":32,"elements":[]},{"c":119,"elements":[]},{"c":111,"elements":[]},{"c":110,"elements":[]},{"c":100,"elements":[]},{"c":101,"elements":[]},{"c":114,"elements":[]},{"c":46,"elements":[]},{"c":10,"elements":[]}],"StringContent":[{"s":"I wonder if you wonder.\n","elements":[]}]}],"CurrentTextSegment":0},{"Identifier":"34","StartTime":143.33200073242188,"EndTime":145.75100708007813,"RegionFeature":"","CueElement":{"Name":"","Value":""},"TextSegments":[{"Content":[{"c":73,"elements":[{"Name":"i","Value":""}]},{"c":116,"elements":[{"Name":"i","Value":""}]},{"c":32,"elements":[{"Name":"i","Value":""}]},{"c":119,"elements":[{"Name":"i","Value":""}]},{"c":97,"elements":[{"Name":"i","Value":""}]},{"c":115,"elements":[{"Name":"i","Value":""}]},{"c":32,"elements":[{"Name":"i","Value":""}]},{"c":97,"elements":[{"Name":"i","Value":""}]},{"c":32,"elements":[{"Name":"i","Value":""}]},{"c":104,"elements":[{"Name":"i","Value":""}]},{"c":111,"elements":[{"Name":"i","Value":""}]},{"c":116,"elements":[{"Name":"i","Value":""}]},{"c":32,"elements":[{"Name":"i","Value":""}]},{"c":97,"elements":[{"Name":"i","Value":""}]},{"c":102,"elements":[{"Name":"i","Value":""}]},{"c":116,"elements":[{"Name":"i","Value":""}]},{"c":101,"elements":[{"Name":"i","Value":""}]},{"c":114,"elements":[{"Name":"i","Value":""}]},{"c":110,"elements":[{"Name":"i","Value":""}]},{"c":111,"elements":[{"Name":"i","Value":""}]},{"c":111,"elements":[{"Name":"i","Value":""}]},{"c":110,"elements":[{"Name":"i","Value":""}]},{"c":10,"elements":[]},{"c":97,"elements":[]},{"c":110,"elements":[]},{"c":100,"elements":[]},{"c":32,"elements":[]},{"c":73,"elements":[]},{"c":32,"elements":[]},{"c":99,"elements":[]},{"c":97,"elements":[]},{"c":110,"elements":[]},{"c":32,"elements":[]},{"c":115,"elements":[]},{"c":116,"elements":[]},{"c":105,"elements":[]},{"c":108,"elements":[]},{"c":108,"elements":[]},{"c":32,"elements":[]},{"c":114,"elements":[]},{"c":101,"elements":[]},{"c":109,"elements":[]},{"c":101,"elements":[]},{"c":109,"elements":[]},{"c":98,"elements":[]},{"c":101,"elements":[]},{"c":114,"elements":[]},{"c":46,"elements":[]},{"c":46,"elements":[]},{"c":46,"elements":[]},{"c":10,"elements":[]}],"StringContent":[{"s":"It was a hot afternoon","elements":[{"Name":"i","Value":""}]},{"s":"\nand I can still remember...\n","elements":[]}]}],"CurrentTextSegment":0},{"Identifier":"35","StartTime":145.83399963378907,"EndTime":148.75399780273438,"RegionFeature":"","CueElement":{"Name":"","Value":""},"TextSegments":[{"Content":[{"c":116,"elements":[{"Name":"i","Value":""}]},{"c":104,"elements":[{"Name":"i","Value":""}]},{"c":101,"elements":[{"Name":"i","Value":""}]},{"c":32,"elements":[{"Name":"i","Value":""}]},{"c":115,"elements":[{"Name":"i","Value":""}]},{"c":109,"elements":[{"Name":"i","Value":""}]},{"c":101,"elements":[{"Name":"i","Value":""}]},{"c":108,"elements":[{"Name":"i","Value":""}]},{"c":108,"elements":[{"Name":"i","Value":""}]},{"c":32,"elements":[{"Name":"i","Value":""}]},{"c":111,"elements":[{"Name":"i","Value":""}]},{"c":102,"elements":[{"Name":"i","Value":""}]},{"c":32,"elements":[{"Name":"i","Value":""}]},{"c":104,"elements":[{"Name":"i","Value":""}]},{"c":111,"elements":[{"Name":"i","Value":""}]},{"c":110,"elements":[{"Name":"i","Value":""}]},{"c":101,"elements":[{"Name":"i","Value":""}]},{"c":121,"elements":[{"Name":"i","Value":""}]},{"c":115,"elements":[{"Name":"i","Value":""}]},{"c":117,"elements":[{"Name":"i","Value":""}]},{"c":99,"elements":[{"Name":"i","Value":""}]},{"c":107,"elements":[{"Name":"i","Value":""}]},{"c":108,"elements":[{"Name":"i","Value":""}]},{"c":101,"elements":[{"Name":"i","Value":""}]},{"c":10,"elements":[]},{"c":97,"elements":[]},{"c":108,"elements":[]},{"c":108,"elements":[]},{"c":32,"elements":[]},{"c":97,"elements":[]},{"c":108,"elements":[]},{"c":111,"elements":[]},{"c":110,"elements":[]},{"c":103,"elements":[]},{"c":32,"elements":[]},{"c":116,"elements":[]},{"c":104,"elements":[]},{"c":97,"elements":[]},{"c":116,"elements":[]},{"c":32,"elements":[]},{"c":115,"elements":[]},{"c":116,"elements":[]},{"c":114,"elements":[]},{"c":101,"elements":[]},{"c":101,"elements":[]},{"c":116,"elements":[]},{"c":46,"elements":[]},{"c":10,"elements":[]}],"StringContent":[{"s":"the smell of honeysuckle","elements":[{"Name":"i","Value":""}]},{"s":"\nall along that street.\n","elements":[]}]}],"CurrentTextSegment":0}],"TextVariations":["Standard English"],"CurrentVariation":0},{"Name":"Speech2","Cues":[{"Identifier":"","StartTime":0.0,"EndTime":2.0,"RegionFeature":"","CueElement":{"Name":"Caption Box ","Value":""},"TextSegments":[{"Content":[{"c":84,"elements":[{"Name":"v","Value":"Person_Speaking"},{"Name":"b","Value":""}]},{"c":69,"elements":[{"Name":"v","Value":"Person_Speaking"},{"Name":"b","Value":""}]},{"c":88,"elements":[{"Name":"v","Value":"Person_Speaking"},{"Name":"b","Value":""}]},{"c":84,"elements":[{"Name":"v","Value":"Person_Speaking"},{"Name":"b","Value":""}]},{"c":32,"elements":[{"Name":"v","Value":"Person_Speaking"},{"Name":"b","Value":""}]},{"c":72,"elements":[{"Name":"v","Value":"Person_Speaking"},{"Name":"b","Value":""}]},{"c":69,"elements":[{"Name":"v","Value":"Person_Speaking"},{"Name":"b","Value":""}]},{"c":82,"elements":[{"Name":"v","Value":"Person_Speaking"},{"Name":"b","Value":""}]},{"c":69,"elements":[{"Name":"v","Value":"Person_Speaking"},{"Name":"b","Value":""}]},{"c":73,"elements":[{"Name":"v","Value":"Person_Speaking"},{"Name":"b","Value":""},{"Name":"i","Value":""}]},{"c":84,"elements":[{"Name":"v","Value":"Person_Speaking"},{"Name":"b","Value":""},{"Name":"i","Value":""}]},{"c":65,"elements":[{"Name":"v","Value":"Person_Speaking"},{"Name":"b","Value":""},{"Name":"i","Value":""}]},{"c":76,"elements":[{"Name":"v","Value":"Person_Speaking"},{"Name":"b","Value":""},{"Name":"i","Value":""}]},{"c":73,"elements":[{"Name":"v","Value":"Person_Speaking"},{"Name":"b","Value":""},{"Name":"i","Value":""}]},{"c":67,"elements":[{"Name":"v","Value":"Person_Speaking"},{"Name":"b","Value":""},{"Name":"i","Value":""}]},{"c":83,"elements":[{"Name":"v","Value":"Person_Speaking"},{"Name":"b","Value":""},{"Name":"i","Value":""}]},{"c":10,"elements":[]},{"c":84,"elements":[]},{"c":69,"elements":[]},{"c":88,"elements":[]},{"c":84,"elements":[]},{"c":32,"elements":[]},{"c":72,"elements":[]},{"c":69,"elements":[]},{"c":82,"elements":[]},{"c":69,"elements":[]},{"c":85,"elements":[{"Name":"u","Value":""}]},{"c":78,"elements":[{"Name":"u","Value":""}]},{"c":68,"elements":[{"Name":"u","Value":""}]},{"c":69,"elements":[{"Name":"u","Value":""}]},{"c":82,"elements":[{"Name":"u","Value":""}]},{"c":76,"elements":[{"Name":"u","Value":""}]},{"c":73,"elements":[{"Name":"u","Value":""}]},{"c":78,"elements":[{"Name":"u","Value":""}]},{"c":69,"elements":[{"Name":"u","Value":""}]},{"c":84,"elements":[]},{"c":69,"elements":[]},{"c":88,"elements":[]},{"c":84,"elements":[]},{"c":32,"elements":[]},{"c":72,"elements":[]},{"c":69,"elements":[]},{"c":82,"elements":[]},{"c":69,"elements":[]},{"c":46,"elements":[]},{"c":32,"elements":[]},{"c":84,"elements":[]},{"c":104,"elements":[]},{"c":105,"elements":[]},{"c":115,"elements":[]},{"c":116,"elements":[{"Name":"TimeStamp","Value":"1"}]},{"c":101,"elements":[{"Name":"TimeStamp","Value":"1"}]},{"c":120,"elements":[{"Name":"TimeStamp","Value":"1"}]},{"c":116,"elements":[{"Name":"TimeStamp","Value":"1"}]},{"c":119,"elements":[{"Name":"TimeStamp","Value":"2"}]},{"c":105,"elements":[{"Name":"TimeStamp","Value":"2"}]},{"c":108,"elements":[{"Name":"TimeStamp","Value":"2"}]},{"c":108,"elements":[{"Name":"TimeStamp","Value":"2"}]},{"c":97,"elements":[{"Name":"TimeStamp","Value":"3"}]},{"c":112,"elements":[{"Name":"TimeStamp","Value":"3"}]},{"c":112,"elements":[{"Name":"TimeStamp","Value":"3"}]},{"c":101,"elements":[{"Name":"TimeStamp","Value":"3"}]},{"c":97,"elements":[{"Name":"TimeStamp","Value":"3"}]},{"c":114,"elements":[{"Name":"TimeStamp","Value":"3"}]},{"c":111,"elements":[{"Name":"TimeStamp","Value":"4"}]},{"c":118,"elements":[{"Name":"TimeStamp","Value":"4"}]},{"c":101,"elements":[{"Name":"TimeStamp","Value":"4"}]},{"c":114,"elements":[{"Name":"TimeStamp","Value":"4"}]},{"c":54,"elements":[{"Name":"TimeStamp","Value":"5"}]},{"c":115,"elements":[{"Name":"TimeStamp","Value":"6"}]},{"c":101,"elements":[{"Name":"TimeStamp","Value":"6"}]},{"c":99,"elements":[{"Name":"TimeStamp","Value":"6"}]},{"c":111,"elements":[{"Name":"TimeStamp","Value":"6"}]},{"c":110,"elements":[{"Name":"TimeStamp","Value":"6"}]},{"c":100,"elements":[{"Name":"TimeStamp","Value":"6"}]},{"c":115,"elements":[{"Name":"TimeStamp","Value":"6"}]},{"c":46,"elements":[{"Name":"TimeStamp","Value":"6"}]},{"c":10,"elements":[]},{"c":73,"elements":[{"Name":"v.first.loud","Value":"Esme"}]},{"c":116,"elements":[{"Name":"v.first.loud","Value":"Esme"}]},{"c":8217,"elements":[{"Name":"v.first.loud","Value":"Esme"}]},{"c":115,"elements":[{"Name":"v.first.loud","Value":"Esme"}]},{"c":32,"elements":[{"Name":"v.first.loud","Value":"Esme"}]},{"c":97,"elements":[{"Name":"v.first.loud","Value":"Esme"}]},{"c":32,"elements":[{"Name":"v.first.loud","Value":"Esme"}]},{"c":98,"elements":[{"Name":"v.first.loud","Value":"Esme"}]},{"c":108,"elements":[{"Name":"v.first.loud","Value":"Esme"}]},{"c":117,"elements":[{"Name":"v.first.loud","Value":"Esme"}]},{"c":101,"elements":[{"Name":"v.first.loud","Value":"Esme"}]},{"c":32,"elements":[{"Name":"v.first.loud","Value":"Esme"}]},{"c":97,"elements":[{"Name":"v.first.loud","Value":"Esme"}]},{"c":112,"elements":[{"Name":"v.first.loud","Value":"Esme"}]},{"c":112,"elements":[{"Name":"v.first.loud","Value":"Esme"}]},{"c":108,"elements":[{"Name":"v.first.loud","Value":"Esme"}]},{"c":101,"elements":[{"Name":"v.first.loud","Value":"Esme"}]},{"c":32,"elements":[{"Name":"v.first.loud","Value":"Esme"}]},{"c":116,"elements":[{"Name":"v.first.loud","Value":"Esme"}]},{"c":114,"elements":[{"Name":"v.first.loud","Value":"Esme"}]},{"c":101,"elements":[{"Name":"v.first.loud","Value":"Esme"}]},{"c":101,"elements":[{"Name":"v.first.loud","Value":"Esme"}]},{"c":33,"elements":[{"Name":"v.first.loud","Value":"Esme"}]},{"c":10,"elements":[]}],"StringContent":[{"s":"TEXT HERE","elements":[{"Name":"v","Value":"Person_Speaking"},{"Name":"b","Value":""}]},{"s":"ITALICS","elements":[{"Name":"v","Value":"Person_Speaking"},{"Name":"b","Value":""},{"Name":"i","Value":""}]},{"s":"\nTEXT HERE","elements":[]},{"s":"UNDERLINE","elements":[{"Name":"u","Value":""}]},{"s":"TEXT HERE. This","elements":[]},{"s":"text","elements":[{"Name":"TimeStamp","Value":"1"}]},{"s":"will","elements":[{"Name":"TimeStamp","Value":"2"}]},{"s":"appear","elements":[{"Name":"TimeStamp","Value":"3"}]},{"s":"over","elements":[{"Name":"TimeStamp","Value":"4"}]},{"s":"6","elements":[{"Name":"TimeStamp","Value":"5"}]},{"s":"seconds.","elements":[{"Name":"TimeStamp","Value":"6"}]},{"s":"\n","elements":[]},{"s":"Its a blue apple tree!","elements":[{"Name":"v.first.loud","Value":"Esme"}]},{"s":"\n","elements":[]}]}],"CurrentTextSegment":0},{"Identifier":"","StartTime":2.0,"EndTime":3.0,"RegionFeature":"","CueElement":{"Name":"Caption Box  2","Value":""},"TextSegments":[{"Content":[{"c":84,"elements":[]},{"c":69,"elements":[]},{"c":88,"elements":[]},{"c":84,"elements":[]},{"c":32,"elements":[]},{"c":72,"elements":[]},{"c":69,"elements":[]},{"c":82,"elements":[]},{"c":69,"elements":[]},{"c":10,"elements":[]}],"StringContent":[{"s":"TEXT HERE\n","elements":[]}]}],"CurrentTextSegment":0},{"Identifier":"","StartTime":3.0,"EndTime":4.0,"RegionFeature":"","CueElement":{"Name":"","Value":""},"TextSegments":[{"Content":[{"c":84,"elements":[]},{"c":69,"elements":[]},{"c":88,"elements":[]},{"c":84,"elements":[]},{"c":32,"elements":[]},{"c":72,"elements":[]},{"c":69,"elements":[]},{"c":82,"elements":[]},{"c":69,"elements":[]},{"c":66,"elements":[{"Name":"b","Value":""}]},{"c":79,"elements":[{"Name":"b","Value":""}]},{"c":76,"elements":[{"Name":"b","Value":""}]},{"c":68,"elements":[{"Name":"b","Value":""}]},{"c":84,"elements":[]},{"c":69,"elements":[]},{"c":88,"elements":[]},{"c":84,"elements":[]},{"c":32,"elements":[]},{"c":72,"elements":[]},{"c":69,"elements":[]},{"c":82,"elements":[]},{"c":69,"elements":[]},{"c":46,"elements":[]},{"c":10,"elements":[]}],"StringContent":[{"s":"TEXT HERE","elements":[]},{"s":"BOLD","elements":[{"Name":"b","Value":""}]},{"s":"TEXT HERE.\n","elements":[]}]}],"CurrentTextSegment":0},{"Identifier":"","StartTime":4.0,"EndTime":12.0,"RegionFeature":"","CueElement":{"Name":"Caption Box  3","Value":""},"TextSegments":[{"Content":[{"c":84,"elements":[]},{"c":69,"elements":[]},{"c":88,"elements":[]},{"c":84,"elements":[]},{"c":32,"elements":[]},{"c":72,"elements":[]},{"c":69,"elements":[]},{"c":82,"elements":[]},{"c":69,"elements":[]},{"c":85,"elements":[{"Name":"u","Value":""}]},{"c":78,"elements":[{"Name":"u","Value":""}]},{"c":68,"elements":[{"Name":"u","Value":""}]},{"c":69,"elements":[{"Name":"u","Value":""}]},{"c":82,"elements":[{"Name":"u","Value":""}]},{"c":76,"elements":[{"Name":"u","Value":""}]},{"c":73,"elements":[{"Name":"u","Value":""}]},{"c":78,"elements":[{"Name":"u","Value":""}]},{"c":69,"elements":[{"Name":"u","Value":""}]},{"c":84,"elements":[]},{"c":69,"elements":[]},{"c":88,"elements":[]},{"c":84,"elements":[]},{"c":32,"elements":[]},{"c":72,"elements":[]},{"c":69,"elements":[]},{"c":82,"elements":[]},{"c":69,"elements":[]},{"c":46,"elements":[]},{"c":32,"elements":[]},{"c":84,"elements":[]},{"c":104,"elements":[]},{"c":105,"elements":[]},{"c":115,"elements":[]},{"c":116,"elements":[{"Name":"TimeStamp","Value":"1"}]},{"c":101,"elements":[{"Name":"TimeStamp","Value":"1"}]},{"c":120,"elements":[{"Name":"TimeStamp","Value":"1"}]},{"c":116,"elements":[{"Name":"TimeStamp","Value":"1"}]},{"c":119,"elements":[{"Name":"TimeStamp","Value":"2"}]},{"c":105,"elements":[{"Name":"TimeStamp","Value":"2"}]},{"c":108,"elements":[{"Name":"TimeStamp","Value":"2"}]},{"c":108,"elements":[{"Name":"TimeStamp","Value":"2"}]},{"c":97,"elements":[{"Name":"TimeStamp","Value":"3"}]},{"c":112,"elements":[{"Name":"TimeStamp","Value":"3"}]},{"c":112,"elements":[{"Name":"TimeStamp","Value":"3"}]},{"c":101,"elements":[{"Name":"TimeStamp","Value":"3"}]},{"c":97,"elements":[{"Name":"TimeStamp","Value":"3"}]},{"c":114,"elements":[{"Name":"TimeStamp","Value":"3"}]},{"c":111,"elements":[{"Name":"TimeStamp","Value":"4"}]},{"c":118,"elements":[{"Name":"TimeStamp","Value":"4"}]},{"c":101,"elements":[{"Name":"TimeStamp","Value":"4"}]},{"c":114,"elements":[{"Name":"TimeStamp","Value":"4"}]},{"c":54,"elements":[{"Name":"TimeStamp","Value":"5"}]},{"c":115,"elements":[{"Name":"TimeStamp","Value":"6"}]},{"c":101,"elements":[{"Name":"TimeStamp","Value":"6"}]},{"c":99,"elements":[{"Name":"TimeStamp","Value":"6"}]},{"c":111,"elements":[{"Name":"TimeStamp","Value":"6"}]},{"c":110,"elements":[{"Name":"TimeStamp","Value":"6"}]},{"c":100,"elements":[{"Name":"TimeStamp","Value":"6"}]},{"c":115,"elements":[{"Name":"TimeStamp","Value":"6"}]},{"c":46,"elements":[{"Name":"TimeStamp","Value":"6"}]},{"c":10,"elements":[]}],"StringContent":[{"s":"TEXT HERE","elements":[]},{"s":"UNDERLINE","elements":[{"Name":"u","Value":""}]},{"s":"TEXT HERE. This","elements":[]},{"s":"text","elements":[{"Name":"TimeStamp","Value":"1"}]},{"s":"will","elements":[{"Name":"TimeStamp","Value":"2"}]},{"s":"appear","elements":[{"Name":"TimeStamp","Value":"3"}]},{"s":"over","elements":[{"Name":"TimeStamp","Value":"4"}]},{"s":"6","elements":[{"Name":"TimeStamp","Value":"5"}]},{"s":"seconds.","elements":[{"Name":"TimeStamp","Value":"6"}]},{"s":"\n","elements":[]}]}],"CurrentTextSegment":0},{"Identifier":"","StartTime":12.0,"EndTime":14.0,"RegionFeature":"","CueElement":{"Name":"","Value":""},"TextSegments":[{"Content":[{"c":83,"elements":[]},{"c":117,"elements":[]},{"c":114,"elements":[]},{"c":32,"elements":[]},{"c":108,"elements":[]},{"c":101,"elements":[]},{"c":115,"elements":[]},{"c":112,"elements":[{"Name":"i.foreignphrase","Value":""},{"Name":"lang","Value":"en"}]},{"c":108,"elements":[{"Name":"i.foreignphrase","Value":""},{"Name":"lang","Value":"en"}]},{"c":97,"elements":[{"Name":"i.foreignphrase","Value":""},{"Name":"lang","Value":"en"}]},{"c":121,"elements":[{"Name":"i.foreignphrase","Value":""},{"Name":"lang","Value":"en"}]},{"c":103,"elements":[{"Name":"i.foreignphrase","Value":""},{"Name":"lang","Value":"en"}]},{"c":114,"elements":[{"Name":"i.foreignphrase","Value":""},{"Name":"lang","Value":"en"}]},{"c":111,"elements":[{"Name":"i.foreignphrase","Value":""},{"Name":"lang","Value":"en"}]},{"c":117,"elements":[{"Name":"i.foreignphrase","Value":""},{"Name":"lang","Value":"en"}]},{"c":110,"elements":[{"Name":"i.foreignphrase","Value":""},{"Name":"lang","Value":"en"}]},{"c":100,"elements":[{"Name":"i.foreignphrase","Value":""},{"Name":"lang","Value":"en"}]},{"c":44,"elements":[{"Name":"i.foreignphrase","Value":""}]},{"c":32,"elements":[{"Name":"i.foreignphrase","Value":""}]},{"c":105,"elements":[{"Name":"i.foreignphrase","Value":""}]},{"c":99,"elements":[{"Name":"i.foreignphrase","Value":""}]},{"c":105,"elements":[{"Name":"i.foreignphrase","Value":""}]},{"c":32,"elements":[{"Name":"i.foreignphrase","Value":""}]},{"c":224,"elements":[{"Name":"i.foreignphrase","Value":""}]},{"c":32,"elements":[{"Name":"i.foreignphrase","Value":""}]},{"c":77,"elements":[{"Name":"i.foreignphrase","Value":""}]},{"c":111,"elements":[{"Name":"i.foreignphrase","Value":""}]},{"c":110,"elements":[{"Name":"i.foreignphrase","Value":""}]},{"c":116,"elements":[{"Name":"i.foreignphrase","Value":""}]},{"c":112,"elements":[{"Name":"i.foreignphrase","Value":""}]},{"c":101,"elements":[{"Name":"i.foreignphrase","Value":""}]},{"c":108,"elements":[{"Name":"i.foreignphrase","Value":""}]},{"c":108,"elements":[{"Name":"i.foreignphrase","Value":""}]},{"c":105,"elements":[{"Name":"i.foreignphrase","Value":""}]},{"c":101,"elements":[{"Name":"i.foreignphrase","Value":""}]},{"c":114,"elements":[{"Name":"i.foreignphrase","Value":""}]},{"c":10,"elements":[]}],"StringContent":[{"s":"Sur les","elements":[]},{"s":"playground","elements":[{"Name":"i.foreignphrase","Value":""},{"Name":"lang","Value":"en"}]},{"s":", ici  Montpellier","elements":[{"Name":"i.foreignphrase","Value":""}]},{"s":"\n","elements":[]}]}],"CurrentTextSegment":0},{"Identifier":"","StartTime":14.0,"EndTime":16.0,"RegionFeature":"","CueElement":{"Name":"","Value":""},"TextSegments":[{"Content":[{"c":73,"elements":[{"Name":"v.first.loud","Value":"Esme"}]},{"c":116,"elements":[{"Name":"v.first.loud","Value":"Esme"}]},{"c":8217,"elements":[{"Name":"v.first.loud","Value":"Esme"}]},{"c":115,"elements":[{"Name":"v.first.loud","Value":"Esme"}]},{"c":32,"elements":[{"Name":"v.first.loud","Value":"Esme"}]},{"c":97,"elements":[{"Name":"v.first.loud","Value":"Esme"}]},{"c":32,"elements":[{"Name":"v.first.loud","Value":"Esme"}]},{"c":98,"elements":[{"Name":"v.first.loud","Value":"Esme"}]},{"c":108,"elements":[{"Name":"v.first.loud","Value":"Esme"}]},{"c":117,"elements":[{"Name":"v.first.loud","Value":"Esme"}]},{"c":101,"elements":[{"Name":"v.first.loud","Value":"Esme"}]},{"c":32,"elements":[{"Name":"v.first.loud","Value":"Esme"}]},{"c":97,"elements":[{"Name":"v.first.loud","Value":"Esme"}]},{"c":112,"elements":[{"Name":"v.first.loud","Value":"Esme"}]},{"c":112,"elements":[{"Name":"v.first.loud","Value":"Esme"}]},{"c":108,"elements":[{"Name":"v.first.loud","Value":"Esme"}]},{"c":101,"elements":[{"Name":"v.first.loud","Value":"Esme"}]},{"c":32,"elements":[{"Name":"v.first.loud","Value":"Esme"}]},{"c":116,"elements":[{"Name":"v.first.loud","Value":"Esme"}]},{"c":114,"elements":[{"Name":"v.first.loud","Value":"Esme"}]},{"c":101,"elements":[{"Name":"v.first.loud","Value":"Esme"}]},{"c":101,"elements":[{"Name":"v.first.loud","Value":"Esme"}]},{"c":33,"elements":[{"Name":"v.first.loud","Value":"Esme"}]},{"c":10,"elements":[]}],"StringContent":[{"s":"Its a blue apple tree!","elements":[{"Name":"v.first.loud","Value":"Esme"}]},{"s":"\n","elements":[]}]}],"CurrentTextSegment":0},{"Identifier":"","StartTime":16.0,"EndTime":18.0,"RegionFeature":"","CueElement":{"Name":"Caption Box  4","Value":""},"TextSegments":[{"Content":[{"c":87,"elements":[]},{"c":104,"elements":[]},{"c":101,"elements":[]},{"c":114,"elements":[]},{"c":101,"elements":[]},{"c":32,"elements":[]},{"c":100,"elements":[]},{"c":105,"elements":[]},{"c":100,"elements":[]},{"c":32,"elements":[]},{"c":104,"elements":[]},{"c":101,"elements":[]},{"c":32,"elements":[]},{"c":103,"elements":[]},{"c":111,"elements":[]},{"c":63,"elements":[]},{"c":10,"elements":[]}],"StringContent":[{"s":"Where did he go?\n","elements":[]}]}],"CurrentTextSegment":0},{"Identifier":"","StartTime":18.0,"EndTime":20.0,"RegionFeature":"","CueElement":{"Name":"Caption Box  5","Value":""},"TextSegments":[{"Content":[{"c":73,"elements":[]},{"c":32,"elements":[]},{"c":116,"elements":[]},{"c":104,"elements":[]},{"c":105,"elements":[]},{"c":110,"elements":[]},{"c":107,"elements":[]},{"c":32,"elements":[]},{"c":104,"elements":[]},{"c":101,"elements":[]},{"c":32,"elements":[]},{"c":119,"elements":[]},{"c":101,"elements":[]},{"c":110,"elements":[]},{"c":116,"elements":[]},{"c":32,"elements":[]},{"c":100,"elements":[]},{"c":111,"elements":[]},{"c":119,"elements":[]},{"c":110,"elements":[]},{"c":32,"elements":[]},{"c":116,"elements":[]},{"c":104,"elements":[]},{"c":105,"elements":[]},{"c":115,"elements":[]},{"c":32,"elements":[]},{"c":108,"elements":[]},{"c":97,"elements":[]},{"c":110,"elements":[]},{"c":101,"elements":[]},{"c":46,"elements":[]},{"c":10,"elements":[]}],"StringContent":[{"s":"I think he went down this lane.\n","elements":[]}]}],"CurrentTextSegment":0},{"Identifier":"","StartTime":20.0,"EndTime":22.0,"RegionFeature":"","CueElement":{"Name":"Caption Box  6","Value":""},"TextSegments":[{"Content":[{"c":87,"elements":[]},{"c":104,"elements":[]},{"c":97,"elements":[]},{"c":116,"elements":[]},{"c":32,"elements":[]},{"c":97,"elements":[]},{"c":114,"elements":[]},{"c":101,"elements":[]},{"c":32,"elements":[]},{"c":121,"elements":[]},{"c":111,"elements":[]},{"c":117,"elements":[]},{"c":32,"elements":[]},{"c":119,"elements":[]},{"c":97,"elements":[]},{"c":105,"elements":[]},{"c":116,"elements":[]},{"c":105,"elements":[]},{"c":110,"elements":[]},{"c":103,"elements":[]},{"c":32,"elements":[]},{"c":102,"elements":[]},{"c":111,"elements":[]},{"c":114,"elements":[]},{"c":63,"elements":[]},{"c":10,"elements":[]}],"StringContent":[{"s":"What are you waiting for?\n","elements":[]}]}],"CurrentTextSegment":0},{"Identifier":"","StartTime":22.0,"EndTime":24.0,"RegionFeature":"Region fred","CueElement":{"Name":"Caption Box  7","Value":""},"TextSegments":[{"Content":[{"c":72,"elements":[{"Name":"v","Value":"Fred"}]},{"c":105,"elements":[{"Name":"v","Value":"Fred"}]},{"c":44,"elements":[{"Name":"v","Value":"Fred"}]},{"c":32,"elements":[{"Name":"v","Value":"Fred"}]},{"c":109,"elements":[{"Name":"v","Value":"Fred"}]},{"c":121,"elements":[{"Name":"v","Value":"Fred"}]},{"c":32,"elements":[{"Name":"v","Value":"Fred"}]},{"c":110,"elements":[{"Name":"v","Value":"Fred"}]},{"c":97,"elements":[{"Name":"v","Value":"Fred"}]},{"c":109,"elements":[{"Name":"v","Value":"Fred"}]},{"c":101,"elements":[{"Name":"v","Value":"Fred"}]},{"c":32,"elements":[{"Name":"v","Value":"Fred"}]},{"c":105,"elements":[{"Name":"v","Value":"Fred"}]},{"c":115,"elements":[{"Name":"v","Value":"Fred"}]},{"c":32,"elements":[{"Name":"v","Value":"Fred"}]},{"c":70,"elements":[{"Name":"v","Value":"Fred"}]},{"c":114,"elements":[{"Name":"v","Value":"Fred"}]},{"c":101,"elements":[{"Name":"v","Value":"Fred"}]},{"c":100,"elements":[{"Name":"v","Value":"Fred"}]},{"c":10,"elements":[]}],"StringContent":[{"s":"Hi, my name is Fred","elements":[{"Name":"v","Value":"Fred"}]},{"s":"\n","elements":[]}]}],"CurrentTextSegment":0},{"Identifier":"","StartTime":24.0,"EndTime":26.0,"RegionFeature":"Region bill","CueElement":{"Name":"Caption Box  8","Value":""},"TextSegments":[{"Content":[{"c":72,"elements":[{"Name":"v","Value":"Bill"}]},{"c":105,"elements":[{"Name":"v","Value":"Bill"}]},{"c":44,"elements":[{"Name":"v","Value":"Bill"}]},{"c":32,"elements":[{"Name":"v","Value":"Bill"}]},{"c":73,"elements":[{"Name":"v","Value":"Bill"}]},{"c":8217,"elements":[{"Name":"v","Value":"Bill"}]},{"c":109,"elements":[{"Name":"v","Value":"Bill"}]},{"c":32,"elements":[{"Name":"v","Value":"Bill"}]},{"c":66,"elements":[{"Name":"v","Value":"Bill"}]},{"c":105,"elements":[{"Name":"v","Value":"Bill"}]},{"c":108,"elements":[{"Name":"v","Value":"Bill"}]},{"c":108,"elements":[{"Name":"v","Value":"Bill"}]},{"c":10,"elements":[]}],"StringContent":[{"s":"Hi, Im Bill","elements":[{"Name":"v","Value":"Bill"}]},{"s":"\n","elements":[]}]}],"CurrentTextSegment":0}],"TextVariations":["Standard English"],"CurrentVariation":0}]}